{
  "name": "list_messages",
  "description": "List messages from a specific chat with pagination support.",
  "inputSchema": {
    "type": "object",
    "properties": {
      "chatID": {
        "type": "string",
        "description": "Unique identifier of the chat."
      },
      "cursor": {
        "type": "string",
        "description": "Opaque pagination cursor; do not inspect. Use together with 'direction'."
      },
      "direction": {
        "type": "string",
        "description": "Pagination direction used with 'cursor': 'before' fetches older results, 'after' fetches newer results. Defaults to 'before' when only 'cursor' is provided.",
        "enum": [
          "after",
          "before"
        ]
      }
    },
    "required": [
      "chatID"
    ]
  }
}