{
  "name": "mcp-add",
  "description": "Add a new MCP server to the session. \nThe server must exist in the catalog.",
  "inputSchema": {
    "type": "object",
    "required": [
      "name"
    ],
    "properties": {
      "activate": {
        "type": "boolean",
        "description": "Activate all of the server's tools in the current session",
        "default": true
      },
      "name": {
        "type": "string",
        "description": "Name of the MCP server to add to the registry (must exist in catalog)"
      }
    }
  }
}