{
  "business_name": "Charlie's Angels Hair Salon",
  "slug": "charlies-angels-hair-salon-college-park",
  "category": "Hair Salon",
  "city": "College Park, GA",
  "address": "5725 Old National Hwy #1, College Park, GA 30349",
  "phone_e164": "+14045148719",
  "phone_pretty": "(404) 514-8719",
  "rating": "4.8",
  "review_count": "208",
  "rating_primary_source": "Birdeye",
  "accent_color": "#C8A24B",
  "accent_dark": "#3A1B2E",
  "brand_angle": "College Park's go-to for flawless silk presses, sew-ins, and natural-hair artistry — finally with a brand as polished as the work.",
  "web_brand_status": "weak",
  "current_url": "https://charlies-angels-hair-salon.ueniweb.com/",
  "services": [
    {
      "title": "Silk Press",
      "desc": "Sleek, frizz-free silk presses that leave natural hair smooth, shiny, and full of movement."
    },
    {
      "title": "Sew-In & Weave Extensions",
      "desc": "Custom sew-ins and micro-link installs for length, volume, and a seamless, natural finish."
    },
    {
      "title": "Natural Hair Care",
      "desc": "Healthy-hair treatments, conditioning, and styling tailored to natural textures and protective looks."
    }
  ],
  "rating_sources": [
    "Birdeye"
  ],
  "source_urls": [
    "https://reviews.birdeye.com/charlies-angels-hair-salon-170100401617031",
    "https://www.bestprosintown.com/ga/college-park/charlies-angels-hair-salon-/",
    "https://www.fresha.com/lvp/charlies-angels-hair-salon-old-national-highway-college-park-wraw3v",
    "https://www.yelp.com/biz/charlies-angels-hair-salon-college-park-13",
    "https://charlies-angels-hair-salon.ueniweb.com/",
    "https://charlieangelssalon.glossgenius.com/about",
    "https://foursquare.com/v/charlies-angels-hair-salon/59d3d9e39e0d540b4ec82a73"
  ],
  "assets": {
    "hero_video": "assets/hero.mp4",
    "hero_poster": "assets/hero.png",
    "logo": "assets/logo.png"
  },
  "data_integrity": "Rating (4.8 / 208 reviews) verified live on Birdeye (reviews.birdeye.com/charlies-angels-hair-salon-170100401617031) on 2026-05-31. Single-source figure — no cross-platform aggregate claimed, no individual review quotes fabricated. BestProsInTown showed 129 reviews and Fresha/Yelp showed no public count, so only the reproducible Birdeye figure is displayed.",
  "year": "2026",
  "built_by": "Self Exec / Executive Leverage"
}
